License.txt
MANIFEST.in
README.rst
Readme.rst
setup.py
chamomile/__init__.py
chamomile/test.py
chamomile.egg-info/PKG-INFO
chamomile.egg-info/SOURCES.txt
chamomile.egg-info/dependency_links.txt
chamomile.egg-info/top_level.txt