Metadata-Version: 1.0
Name: chamomile
Version: 1.0.1
Summary: Jasmine-style assertions for unittest
Home-page: https://github.com/enaeseth/chamomile
Author: Eric Naeseth
Author-email: eric@naeseth.com
License: MIT
Platform: UNKNOWN
Classifier: Development Status :: 5 - Production/Stable
Classifier: License :: OSI Approved :: MIT License
Classifier: Topic :: Software Development :: Testing
Classifier: Programming Language :: Python :: 2.5
Classifier: Programming Language :: Python :: 2.6
Classifier: Programming Language :: Python :: 2.7
Classifier: Programming Language :: Python :: 3
Classifier: Programming Language :: Python :: Implementation :: CPython
Classifier: Programming Language :: Python :: Implementation :: PyPy
